Auto/Feature_engineering.py
Auto/__init__.py
Auto/myfunctions.py
simplifykm-0.1.9.dist-info/METADATA
simplifykm-0.1.9.dist-info/WHEEL
simplifykm-0.1.9.dist-info/top_level.txt
simplifykm-0.1.9.dist-info/RECORD
