Metadata-Version: 2.4
Name: simplifykm
Version: 0.1.9
Summary: This library automates tasks.
Author: Khemraj Mangal
Requires-Dist: pandas
Requires-Dist: numpy
Requires-Dist: scikit-learn
Requires-Dist: matplotlib
Requires-Dist: seaborn
Dynamic: author
Dynamic: requires-dist
Dynamic: summary
